frio/__init__.py
frio/frio.py
frio-0.1.0.dist-info/METADATA
frio-0.1.0.dist-info/WHEEL
frio-0.1.0.dist-info/RECORD
